{"file":"other.png","frames":{
"4":{"x":968,"y":118,"w":32,"h":44,"offX":0,"offY":0,"sourceW":32,"sourceH":44},
"5":{"x":0,"y":0,"w":750,"h":213,"offX":0,"offY":0,"sourceW":750,"sourceH":213},
"6":{"x":231,"y":255,"w":206,"h":69,"offX":0,"offY":0,"sourceW":206,"sourceH":69},
"avatardefault":{"x":231,"y":324,"w":100,"h":100,"offX":0,"offY":0,"sourceW":100,"sourceH":100},
"defen":{"x":437,"y":293,"w":337,"h":41,"offX":0,"offY":0,"sourceW":337,"sourceH":41},
"game_guanggao_weizhong":{"x":946,"y":90,"w":10,"h":10,"offX":0,"offY":0,"sourceW":10,"sourceH":10},
"game_guanggao_xuanzhong":{"x":956,"y":90,"w":10,"h":10,"offX":0,"offY":0,"sourceW":10,"sourceH":10},
"line":{"x":0,"y":213,"w":750,"h":42,"offX":0,"offY":0,"sourceW":750,"sourceH":42},
"pause_txt":{"x":750,"y":0,"w":196,"h":108,"offX":0,"offY":0,"sourceW":196,"sourceH":108},
"prepareBg_1":{"x":0,"y":255,"w":103,"h":177,"offX":0,"offY":0,"sourceW":103,"sourceH":177},
"prepareBg-front":{"x":859,"y":108,"w":109,"h":179,"offX":0,"offY":6,"sourceW":109,"sourceH":185},
"prepareBg":{"x":750,"y":108,"w":109,"h":185,"offX":0,"offY":0,"sourceW":109,"sourceH":185},
"prompt_bg1":{"x":774,"y":293,"w":70,"h":60,"offX":0,"offY":0,"sourceW":70,"sourceH":60},
"prop_lock":{"x":968,"y":162,"w":28,"h":41,"offX":0,"offY":0,"sourceW":28,"sourceH":41},
"prop_zhadan":{"x":331,"y":324,"w":57,"h":66,"offX":9,"offY":2,"sourceW":75,"sourceH":68},
"propboomP":{"x":1000,"y":142,"w":24,"h":24,"offX":0,"offY":0,"sourceW":24,"sourceH":24},
"proplaserP":{"x":1000,"y":118,"w":24,"h":24,"offX":0,"offY":0,"sourceW":24,"sourceH":24},
"propranbowP":{"x":946,"y":70,"w":20,"h":20,"offX":2,"offY":2,"sourceW":24,"sourceH":24},
"propraserLine":{"x":103,"y":255,"w":128,"h":127,"offX":0,"offY":0,"sourceW":128,"sourceH":128},
"propselected":{"x":946,"y":0,"w":70,"h":70,"offX":0,"offY":0,"sourceW":70,"sourceH":70},
"proptonghangP":{"x":996,"y":166,"w":24,"h":24,"offX":0,"offY":0,"sourceW":24,"sourceH":24},
"reborn_txt":{"x":859,"y":287,"w":152,"h":74,"offX":0,"offY":0,"sourceW":152,"sourceH":74},
"refresh_prepare":{"x":968,"y":70,"w":48,"h":48,"offX":0,"offY":0,"sourceW":48,"sourceH":48}}}