{"width":512,"SubTexture":[{"frameY":-14,"y":214,"frameWidth":64,"frameX":0,"frameHeight":64,"width":64,"height":38,"name":"images/beamSprite/beamSprite_05","x":67},{"frameY":-14,"y":92,"frameWidth":64,"frameX":0,"frameHeight":64,"width":64,"height":37,"name":"images/beamSprite/beamSprite_04","x":199},{"frameY":-15,"y":1,"frameWidth":64,"frameX":0,"frameHeight":64,"width":64,"height":35,"name":"images/beamSprite/beamSprite_03","x":244},{"frameY":-10,"y":100,"frameWidth":64,"frameX":0,"frameHeight":64,"width":64,"height":47,"name":"images/beamSprite/beamSprite_13","x":133},{"frameY":-16,"y":221,"frameWidth":64,"frameX":0,"frameHeight":64,"width":64,"height":33,"name":"images/beamSprite/beamSprite_02","x":1},{"frameY":-10,"y":164,"frameWidth":64,"frameX":0,"frameHeight":64,"width":64,"height":48,"name":"images/beamSprite/beamSprite_15","x":67},{"frameY":-3,"y":113,"frameWidth":64,"frameX":0,"frameHeight":64,"width":64,"height":54,"name":"images/beamSprite/beamSprite_16","x":1},{"frameY":-16,"y":38,"frameWidth":64,"frameX":0,"frameHeight":64,"width":64,"height":31,"name":"images/beamSprite/beamSprite_01","x":244},{"frameY":-7,"y":113,"frameWidth":64,"frameX":0,"frameHeight":64,"width":64,"height":49,"name":"images/beamSprite/beamSprite_10","x":67},{"frameY":-10,"y":1,"frameWidth":64,"frameX":0,"frameHeight":64,"width":64,"height":48,"name":"images/beamSprite/beamSprite_12","x":112},{"frameY":-9,"y":169,"frameWidth":64,"frameX":0,"frameHeight":64,"width":64,"height":50,"name":"images/beamSprite/beamSprite_14","x":1},{"frameY":-10,"y":47,"frameWidth":64,"frameX":0,"frameHeight":64,"width":64,"height":43,"name":"images/beamSprite/beamSprite_08","x":178},{"frameY":-10,"y":1,"frameWidth":64,"frameX":0,"frameHeight":64,"width":64,"height":44,"name":"images/beamSprite/beamSprite_09","x":178},{"frameY":-11,"y":193,"frameWidth":64,"frameX":0,"frameHeight":64,"width":64,"height":42,"name":"images/beamSprite/beamSprite_07","x":133},{"frameY":-10,"y":149,"frameWidth":64,"frameX":0,"frameHeight":64,"width":64,"height":42,"name":"images/beamSprite/beamSprite_06","x":133},{"frameY":-10,"y":51,"frameWidth":64,"frameX":0,"frameHeight":64,"width":64,"height":47,"name":"images/beamSprite/beamSprite_11","x":112},{"frameY":-10,"y":1,"frameWidth":128,"frameX":-9,"frameHeight":128,"width":109,"height":110,"name":"images/glow04","x":1}],"height":256,"name":"xiaochu_yihang","imagePath":"xiaochu_yihang_tex.png"}